Metadata-Version: 2.1
Name: game-coroutines
Version: 0.1.0
Summary: game_coroutines is a pure-python lib with no dependencies, to simplify calling methods over time on game environments.
Home-page: https://github.com/Ruppy/game_coroutines
Author: Leonardo Baptista
Author-email: leonardoobaptistaa@gmail.com
License: MIT
Keywords: pygame arcade coroutines routines sprites
Classifier: Development Status :: 5 - Production/Stable
License-File: LICENSE
